pylasu/__init__.py
pylasu/astruntime.py
pylasu/support.py
pylasu/StrumentaLanguageSupport/StrumentaLanguageSupport.py
pylasu/StrumentaLanguageSupport/__init__.py
pylasu/emf/__init__.py
pylasu/emf/metamodel_builder.py
pylasu/emf/model.py
pylasu/mapping/__init__.py
pylasu/mapping/parse_tree_to_ast_transformer.py
pylasu/model/__init__.py
pylasu/model/errors.py
pylasu/model/model.py
pylasu/model/naming.py
pylasu/model/position.py
pylasu/model/processing.py
pylasu/model/reflection.py
pylasu/model/traversing.py
pylasu/parsing/__init__.py
pylasu/parsing/antlr.py
pylasu/parsing/parse_tree.py
pylasu/parsing/results.py
pylasu/playground/__init__.py
pylasu/playground/transpilation_trace.py
pylasu/playground/transpilation_trace_ecore.py
pylasu/reflection/__init__.py
pylasu/reflection/reflection.py
pylasu/testing/__init__.py
pylasu/testing/testing.py
pylasu/transformation/__init__.py
pylasu/transformation/generic_nodes.py
pylasu/transformation/transformation.py
pylasu/validation/__init__.py
pylasu/validation/validation.py
pylasu-0.9.1.dist-info/licenses/LICENSE
pylasu-0.9.1.dist-info/METADATA
pylasu-0.9.1.dist-info/WHEEL
pylasu-0.9.1.dist-info/top_level.txt
pylasu-0.9.1.dist-info/RECORD
