Metadata-Version: 2.4
Name: pylasu
Version: 0.9.1
Summary: Pylasu is an AST Library in the StarLasu family, targeting the Python language.
Author-email: Lorenzo Addazi <lorenzo.addazi@strumenta.com>, Alessio Stalla <alessio.stalla@strumenta.com>, Federico Tomassetti <federico@strumenta.com>
License-Expression: Apache-2.0
Project-URL: Homepage, https://github.com/strumenta/pylasu
Project-URL: Bug Tracker, https://github.com/strumenta/pylasu/issues
Classifier: Programming Language :: Python :: 3
Classifier: Operating System :: OS Independent
Requires-Python: >=3.8
License-File: LICENSE
Provides-Extra: ecore
Requires-Dist: pyecore; extra == "ecore"
Dynamic: license-file
